ecjtu/__init__.py
ecjtu/__main__.py
ecjtu/client.py
ecjtu/constants.py
ecjtu/crud.py
ecjtu/models.py
ecjtu/server/__init__.py
ecjtu/server/api.py
ecjtu/server/auth.py
ecjtu/server/middle.py
ecjtu/server/respose_result.py
ecjtu/server/schema.py
ecjtu/utils/__init__.py
ecjtu/utils/cookie.py
ecjtu/utils/logger.py
ecjtu/utils/singleton.py
ecjtu-0.2.0.dist-info/LICENSE
ecjtu-0.2.0.dist-info/METADATA
ecjtu-0.2.0.dist-info/WHEEL
ecjtu-0.2.0.dist-info/entry_points.txt
ecjtu-0.2.0.dist-info/RECORD
