Metadata-Version: 2.1
Name: ecjtu
Version: 0.2.0
Summary: ECJTU API SDK service
Home-page: https://github.com/Undertone0809/ecjtu
License: MIT
Author: ecjtu
Author-email: zeeland4work@gmail.com
Requires-Python: >=3.8
Classifier: Development Status :: 3 - Alpha
Classifier: Intended Audience :: Developers
Classifier: License :: OSI Approved :: MIT License
Classifier: Operating System :: OS Independent
Classifier: Programming Language :: Python :: 3
Classifier: Programming Language :: Python :: 3.8
Classifier: Programming Language :: Python :: 3.9
Classifier: Programming Language :: Python :: 3.10
Classifier: Programming Language :: Python :: 3.11
Classifier: Programming Language :: Python :: 3.12
Classifier: Topic :: Software Development :: Libraries :: Python Modules
Requires-Dist: beautifulsoup4 (==4.12.3)
Requires-Dist: cushy-storage (==1.3.8) ; python_version >= "3.8" and python_version < "4.0"
Requires-Dist: fastapi (>=0.111.0,<0.112.0)
Requires-Dist: pydantic (>=2.0.0)
Requires-Dist: pyopenssl (==24.1.0)
Requires-Dist: urllib3 (==1.26.18)
Requires-Dist: uvicorn (>=0.29.0,<0.30.0)
Project-URL: Repository, https://github.com/Undertone0809/ecjtu
